<?xml version="1.0" encoding="utf-8"?>
<PokeData xmlns:xsi="http://www.w3.org/2001/XMLSchema-instance" xmlns:xsd="http://www.w3.org/2001/XMLSchema">
	<Name>Snubbull</Name>
	<Level>50</Level>
	<HP>152</HP>
	<Attack>117</Attack>
	<Defense>88</Defense>
	<SpAttack>77</SpAttack>
	<SpDefense>77</SpDefense>
	<Speed>67</Speed>
	<Moves>
		<Move>
			<Name>Strength</Name>
		</Move>
		<Move>
			<Name>Shadow Ball</Name>
		</Move>
		<Move>
			<Name>Charm</Name>
		</Move>
		<Move>
			<Name>Swagger</Name>
		</Move>
	</Moves>
</PokeData>


